{
 "actions": [],
 "autoname": "autoincrement",
 "creation": "2022-09-30 00:26:05.818685",
 "doctype": "DocType",
 "engine": "InnoDB",
 "field_order": [
  "tanggal_transaksi",
  "jenis_transaksi",
  "nominal"
 ],
 "fields": [
  {
   "fieldname": "tanggal_transaksi",
   "fieldtype": "Datetime",
   "in_list_view": 1,
   "label": "Tanggal Transaksi",
   "read_only": 1
  },
  {
   "fieldname": "jenis_transaksi",
   "fieldtype": "Data",
   "in_list_view": 1,
   "label": "Jenis Transaksi",
   "read_only": 1
  },
  {
   "fieldname": "nominal",
   "fieldtype": "Currency",
   "in_list_view": 1,
   "label": "Nominal",
   "read_only": 1
  }
 ],
 "index_web_pages_for_search": 1,
 "istable": 1,
 "links": [],
 "modified": "2022-09-30 01:25:14.291371",
 "modified_by": "Administrator",
 "module": "Invest",
 "name": "Estatement Investasi Transaksi",
 "naming_rule": "Autoincrement",
 "owner": "Administrator",
 "permissions": [],
 "sort_field": "modified",
 "sort_order": "DESC",
 "states": []
}